Workbook

Sheet Assumptions
A1: Assumptions
A3: Revenue growth | B3: 0.08
A4: Gross margin | B4: 0.38
A5: Tax rate | B5: 0.25
A6: Sales to capital | B6: 2.4
A7: Operating cost ratio | B7: 0.62

Sheet Model
A1: Operating model
B4: FY2023A | C4: FY2024A | D4: FY2025A | E4: FY2026E | F4: FY2027E | G4: FY2028E | H4: FY2029E | I4: FY2030E
A5: Units sold | B5: 4.1 | C5: 4.48 | D5: 4.92 | E5: =D5*(1+Assumptions!$B$3) | F5: =E5*(1+Assumptions!$B$3) | G5: =F5*(1+Assumptions!$B$3) | H5: =G5*(1+Assumptions!$B$3) | I5: =H5*(1+Assumptions!$B$3)
A6: Revenue | B6: 182.4 | C6: 204.7 | D6: 228.9 | E6: =D6*(1+Assumptions!$B$3) | F6: =E6*(1+Assumptions!$B$3) | G6: =F6*(1+Assumptions!$B$3) | H6: =G6*(1+Assumptions!$B$3) | I6: =H6*(1+Assumptions!$B$3)
A7: Revenue growth | C7: =C6/B6-1 | D7: =D6/C6-1 | E7: =E6/C6-1 | F7: =F6/E6-1 | G7: =G6/F6-1 | H7: =H6/G6-1 | I7: =I6/H6-1
A8: Cost of goods sold | B8: -115.9 | C8: -128.4 | D8: -141.5 | E8: =-E6*(1-Assumptions!$B$4) | F8: =-F6*(1-Assumptions!$B$4) | G8: =-G6*(1-Assumptions!$B$4) | H8: =-H6*(1-Assumptions!$B$4) | I8: =-I6*(1-Assumptions!$B$4)
A9: Gross profit | E9: =E6*Assumptions!$B$4+0 | F9: =F6*Assumptions!$B$4 | G9: =G6*Assumptions!$B$4 | H9: =H6*Assumptions!$B$4 | I9: =I6*Assumptions!$B$4
A11: Operating costs | E11: =-E6*Assumptions!$B$7 | F11: -140 | G11: =-G6*Assumptions!$B$7 | H11: =-H6*Assumptions!$B$7 | I11: =-I6*Assumptions!$B$7
A12: Sales to capital | E12: =Assumptions!B6 | F12: =F11/F6 | G12: =G11/G6 | H12: =H11/H6 | I12: =I11/I6
A13: Direct cost | D13: -110 | E13: -112
A14: Sundry inputs | E14: =Assumptions!B3 | F14: =Assumptions!B4*2 | G14: =SUM(E6:F6) | H14: =Assumptions!B5
A15: Other cost | D15: -3.2 | E15: -3.4
A16: Total costs | D16: =SUM(D13:D14)
A17: Total costs, correct | E17: =SUM(E13:E16)
A20: Depreciation | E20: =-E6*0.0413 | F20: =-F6*Assumptions!$B$5 | G20: =-G6*Assumptions!$B$5 | H20: =-H6*Assumptions!$B$5 | I20: =-I6*Assumptions!$B$5
A23: Capital expenditure | E23: =-OFFSET(E6,0,0)*Assumptions!$B$6 | F23: =-F6*Assumptions!$B$6 | G23: =-G6*Assumptions!$B$6 | H23: =-H6*Assumptions!$B$6 | I23: =-I6*Assumptions!$B$6
A26: Working capital | E26: =E6*Assumptions!B3 | F26: =F6*Assumptions!$B$3 | G26: =G6*Assumptions!$B$3 | H26: =H6*Assumptions!$B$3 | I26: =I6*Assumptions!$B$3
A30: Legacy line | C30: #REF!
A33: Prior year comparison | E33: =[1]Model!$D$6*1.5
A36: Interest | E36: =F36*0.05 | F36: =E36+1
A39: Per-share | E39: =E6/100*12
