Workbook

Sheet Assumptions
A1: Cascade Industrial Holdings - Model Assumptions
A2: All figures in $mm unless noted. Blue = input. Black = formula. Green = link to another sheet.
A4: Operating assumptions
A5: Revenue growth - FY2026E | B5: 0.118 | C5: Management plan, Nov 2025 board pack
A6: Revenue growth - FY2027E | B6: 0.105 | C6: Management plan, Nov 2025 board pack
A7: Revenue growth - FY2028E | B7: 0.092 | C7: Management plan, Nov 2025 board pack
A8: Revenue growth - FY2029E | B8: 0.08 | C8: Management plan, Nov 2025 board pack
A9: Revenue growth - FY2030E | B9: 0.07 | C9: Management plan, Nov 2025 board pack
A10: Gross margin - steady state | B10: 0.382 | C10: FY2025 actual, held flat
A11: SG&A as % of revenue | B11: 0.128 | C11: Normalised, post-synergy run rate
A12: R&D as % of revenue | B12: 0.054 | C12: Normalised, post-synergy run rate
A13: D&A as % of revenue | B13: 0.041 | C13: Three-year historical average
A14: Capex as % of revenue | B14: 0.036 | C14: Management plan
A15: Change in NWC as % of revenue growth | B15: 0.145 | C15: Historical working capital intensity
A16: Tax rate | B16: 0.25 | C16: Blended federal and state
A18: Valuation assumptions
A19: WACC | B19: 0.098 | C19: CAPM, peer-derived beta
A20: Terminal growth rate | B20: 0.025 | C20: Long-run GDP proxy
A21: Valuation date | B21: 31-Dec-2025 | C21: Assumed close
A23: Capital structure
A24: Total debt | B24: 96.4 | C24: FY2025 balance sheet
A25: Cash and equivalents | B25: 21.7 | C25: FY2025 balance sheet
A26: Diluted shares outstanding (mm) | B26: 42.8 | C26: FY2025 cap table

Sheet Model
A1: Cascade Industrial Holdings - Operating Model
A2: $mm, fiscal year ending 31 December
A4: ($ in millions) | B4: FY2023A | C4: FY2024A | D4: FY2025A | E4: FY2026E | F4: FY2027E | G4: FY2028E | H4: FY2029E | I4: FY2030E
A6: Revenue | B6: 182.4 | C6: 204.7 | D6: 228.9 | E6: =D6*(1+Assumptions!$B$5) -> 255.9102 | F6: =E6*(1+Assumptions!$B$6) -> 282.78077 | G6: =F6*(1+Assumptions!$B$7) -> 308.7966 | H6: =G6*(1+Assumptions!$B$8) -> 333.50033 | I6: =H6*(1+Assumptions!$B$9) -> 356.84535
A7: % growth | C7: =C6/B6-1 -> 0.12225877 | D7: =D6/C6-1 -> 0.11822179 | E7: =E6/D6-1 -> 0.118 | F7: =F6/E6-1 -> 0.105 | G7: =G6/F6-1 -> 0.092 | H7: =H6/G6-1 -> 0.08 | I7: =I6/H6-1 -> 0.07
A9: Cost of goods sold | B9: -115.9 | C9: -128.4 | D9: -141.5 | E9: =-E6*(1-Assumptions!$B$10) -> -158.1525 | F9: =-F6*(1-Assumptions!$B$10) -> -174.75852 | G9: =-G6*(1-Assumptions!$B$10) -> -190.8363 | H9: =-H6*(1-Assumptions!$B$10) -> -206.1032 | I9: =-I6*(1-Assumptions!$B$10) -> -220.53043
A10: Gross profit | B10: =B6+B9 -> 66.5 | C10: =C6+C9 -> 76.3 | D10: =D6+D9 -> 87.4 | E10: =E6+E9 -> 97.757696 | F10: =F6+F9 -> 108.02225 | G10: =G6+G9 -> 117.9603 | H10: =H6+H9 -> 127.39713 | I10: =I6+I9 -> 136.31492
A11: Gross margin % | B11: =B10/B6 -> 0.36458333 | C11: =C10/C6 -> 0.3727406 | D11: =D10/D6 -> 0.38182612 | E11: =E10/E6 -> 0.382 | F11: =F10/F6 -> 0.382 | G11: =G10/G6 -> 0.382 | H11: =H10/H6 -> 0.382 | I11: =I10/I6 -> 0.382
A13: Selling, general and administrative | B13: -26.8 | C13: -29.9 | D13: -32.9 | E13: =-E6*Assumptions!$B$11 -> -32.756506 | F13: =-F6*Assumptions!$B$11 -> -36.195939 | G13: =-G6*Assumptions!$B$11 -> -39.525965 | H13: =-H6*Assumptions!$B$11 -> -42.688042 | I13: =-I6*Assumptions!$B$11 -> -45.676205
A14: Research and development | B14: -10.5 | C14: -11.9 | D14: -13.3 | E14: =-E6*Assumptions!$B$12 -> -13.819151 | F14: =-F6*Assumptions!$B$12 -> -15.270162 | G14: =-G6*Assumptions!$B$12 -> -16.675017 | H14: =-H6*Assumptions!$B$12 -> -18.009018 | I14: =-I6*Assumptions!$B$12 -> -19.269649
A16: Reported EBITDA | B16: =B10+B13+B14 -> 29.2 | C16: =C10+C13+C14 -> 34.5 | D16: =D10+D13+D14 -> 41.2 | E16: =E10+E13+E14 -> 51.18204 | F16: =F10+F13+F14 -> 56.556154 | G16: =G10+G13+G14 -> 61.75932 | H16: =H10+H13+H14 -> 66.700066 | I16: =I10+I13+I14 -> 71.369071
A17: Reported EBITDA margin % | B17: =B16/B6 -> 0.16008772 | C17: =C16/C6 -> 0.16853933 | D17: =D16/D6 -> 0.17999126 | E17: =E16/E6 -> 0.2 | F17: =F16/F6 -> 0.2 | G17: =G16/G6 -> 0.2 | H17: =H16/H6 -> 0.2 | I17: =I16/I6 -> 0.2
A19: EBITDA adjustments
A20: Legal settlement (one-time) | B20: 0 | C20: 2.4 | D20: 0 | E20: 0 | F20: 0 | G20: 0 | H20: 0 | I20: 0 | K20: Settled Q3 FY2024, non-recurring
A21: ERP implementation costs | B21: 0 | C21: 1.1 | D21: 2.8 | E21: 0 | F21: 0 | G21: 0 | H21: 0 | I21: 0 | K21: Programme completes FY2025
A22: Owner compensation normalisation | B22: 1.6 | C22: 1.6 | D22: 1.7 | E22: 0 | F22: 0 | G22: 0 | H22: 0 | I22: 0 | K22: Above-market founder comp
A23: Run-rate synergies - Verity bolt-on | B23: 0 | C23: 0 | D23: 3.2 | E23: 0 | F23: 0 | G23: 0 | H23: 0 | I23: 0 | K23: Annualised, acquired Aug FY2025
A24: Total adjustments | B24: =SUM(B20:B23) -> 1.6 | C24: =SUM(C20:C23) -> 5.1 | D24: =SUM(D20:D23) -> 7.7 | E24: =SUM(E20:E23) -> 0 | F24: =SUM(F20:F23) -> 0 | G24: =SUM(G20:G23) -> 0 | H24: =SUM(H20:H23) -> 0 | I24: =SUM(I20:I23) -> 0
A26: Adjusted EBITDA | B26: =B16+B24 -> 30.8 | C26: =C16+C24 -> 39.6 | D26: =D16+D24 -> 48.9 | E26: =E16+E24 -> 51.18204 | F26: =F16+F24 -> 56.556154 | G26: =G16+G24 -> 61.75932 | H26: =H16+H24 -> 66.700066 | I26: =I16+I24 -> 71.369071
A27: Adjusted EBITDA margin % | B27: =B26/B6 -> 0.16885965 | C27: =C26/C6 -> 0.19345383 | D27: =D26/D6 -> 0.21363041 | E27: =E26/E6 -> 0.2 | F27: =F26/F6 -> 0.2 | G27: =G26/G6 -> 0.2 | H27: =H26/H6 -> 0.2 | I27: =I26/I6 -> 0.2
A29: Unlevered free cash flow
A30: Adjusted EBITDA | B30: =B26 -> 30.8 | C30: =C26 -> 39.6 | D30: =D26 -> 48.9 | E30: =E26 -> 51.18204 | F30: =F26 -> 56.556154 | G30: =G26 -> 61.75932 | H30: =H26 -> 66.700066 | I30: =I26 -> 71.369071
A31: Depreciation and amortisation | B31: =-B6*Assumptions!$B$13 -> -7.4784 | C31: =-C6*Assumptions!$B$13 -> -8.3927 | D31: =-D6*Assumptions!$B$13 -> -9.3849 | E31: =-E6*Assumptions!$B$13 -> -10.492318 | F31: =-F6*Assumptions!$B$13 -> -11.594012 | G31: =-G6*Assumptions!$B$13 -> -12.660661 | H31: =-H6*Assumptions!$B$13 -> -13.673514 | I31: =-I6*Assumptions!$B$13 -> -14.630659
A32: EBIT | B32: =B30+B31 -> 23.3216 | C32: =C30+C31 -> 31.2073 | D32: =D30+D31 -> 39.5151 | E32: =E30+E31 -> 40.689722 | F32: =F30+F31 -> 44.962143 | G32: =G30+G31 -> 49.09866 | H32: =H30+H31 -> 53.026552 | I32: =I30+I31 -> 56.738411
A33: Taxes on EBIT | B33: =-B32*Assumptions!$B$16 -> -5.8304 | C33: =-C32*Assumptions!$B$16 -> -7.801825 | D33: =-D32*Assumptions!$B$16 -> -9.878775 | E33: =-E32*Assumptions!$B$16 -> -10.17243 | F33: =-F32*Assumptions!$B$16 -> -11.240536 | G33: =-G32*Assumptions!$B$16 -> -12.274665 | H33: =-H32*Assumptions!$B$16 -> -13.256638 | I33: =-I32*Assumptions!$B$16 -> -14.184603
A34: Add back D&A | B34: =-B31 -> 7.4784 | C34: =-C31 -> 8.3927 | D34: =-D31 -> 9.3849 | E34: =-E31 -> 10.492318 | F34: =-F31 -> 11.594012 | G34: =-G31 -> 12.660661 | H34: =-H31 -> 13.673514 | I34: =-I31 -> 14.630659
A35: Capital expenditure | B35: =-B6*Assumptions!$B$14 -> -6.5664 | C35: =-C6*Assumptions!$B$14 -> -7.3692 | D35: =-D6*Assumptions!$B$14 -> -8.2404 | E35: =-E6*Assumptions!$B$14 -> -9.2127672 | F35: =-F6*Assumptions!$B$14 -> -10.180108 | G35: =-G6*Assumptions!$B$14 -> -11.116678 | H35: =-H6*Assumptions!$B$14 -> -12.006012 | I35: =-I6*Assumptions!$B$14 -> -12.846433
A36: Change in net working capital | B36: 0 | C36: =-(C6-B6)*Assumptions!$B$15 -> -3.2335 | D36: =-(D6-C6)*Assumptions!$B$15 -> -3.509 | E36: =-(E6-D6)*Assumptions!$B$15 -> -3.916479 | F36: =-(F6-E6)*Assumptions!$B$15 -> -3.8962328 | G36: =-(G6-F6)*Assumptions!$B$15 -> -3.7722955 | H36: =-(H6-G6)*Assumptions!$B$15 -> -3.5820406 | I36: =-(I6-H6)*Assumptions!$B$15 -> -3.3850284
A37: Unlevered free cash flow | B37: =B32+B33+B34+B35+B36 -> 18.4032 | C37: =C32+C33+C34+C35+C36 -> 21.195475 | D37: =D32+D33+D34+D35+D36 -> 27.271825 | E37: =E32+E33+E34+E35+E36 -> 27.880363 | F37: =F32+F33+F34+F35+F36 -> 31.239278 | G37: =G32+G33+G34+G35+G36 -> 34.595682 | H37: =H32+H33+H34+H35+H36 -> 37.855375 | I37: =I32+I33+I34+I35+I36 -> 40.953007

Sheet DCF
A1: Discounted Cash Flow Analysis
A2: $mm. Mid-year convention not applied. Valuation date 31-Dec-2025.
A4: ($ in millions) | B4: FY2026E | C4: FY2027E | D4: FY2028E | E4: FY2029E | F4: FY2030E
A6: Unlevered free cash flow | B6: =Model!E37 -> 27.880363 | C6: =Model!F37 -> 31.239278 | D6: =Model!G37 -> 34.595682 | E6: =Model!H37 -> 37.855375 | F6: =Model!I37 -> 40.953007
A7: Discount period | B7: 1 | C7: 2 | D7: 3 | E7: 4 | F7: 5
A8: Discount factor | B8: =1/(1+Assumptions!$B$19)^B7 -> 0.91074681 | C8: =1/(1+Assumptions!$B$19)^C7 -> 0.82945976 | D8: =1/(1+Assumptions!$B$19)^D7 -> 0.75542783 | E8: =1/(1+Assumptions!$B$19)^E7 -> 0.68800349 | F8: =1/(1+Assumptions!$B$19)^F7 -> 0.62659698
A9: Present value of FCF | B9: =B6*B8 -> 25.391952 | C9: =C6*C8 -> 25.911724 | D9: =D6*D8 -> 26.134541 | E9: =E6*E8 -> 26.04463 | F9: =F6*F8 -> 25.66103
A12: Valuation bridge
A13: Sum of PV of forecast FCF | B13: =SUM(B9:F9) -> 129.14388
A14: Terminal value (Gordon growth) | B14: =F6*(1+Assumptions!$B$20)/(Assumptions!$B$19-Assumptions!$B$20) -> 575.0251
A15: PV of terminal value | B15: =B14*F8 -> 360.30899
A16: Enterprise value | B16: =B13+B15 -> 489.45287
A17: Less: total debt | B17: =-Assumptions!$B$24 -> -96.4
A18: Plus: cash and equivalents | B18: =Assumptions!$B$25 -> 21.7
A19: Equity value | B19: =B16+B17+B18 -> 414.75287
A20: Diluted shares outstanding (mm) | B20: =Assumptions!$B$26 -> 42.8
A21: Implied value per share | B21: =B19/B20 -> 9.6904876
A23: Implied EV / FY2025A Adjusted EBITDA | B23: =B16/Model!D26 -> 10.009261
A24: Implied EV / FY2026E Adjusted EBITDA | B24: =B16/Model!E26 -> 9.5629808

Sheet Comps
A1: Trading Comparables
A2: $mm. Market data as of 28-Nov-2025. Source: company filings, FactSet.
A4: Company | B4: Enterprise value | C4: LTM revenue | D4: LTM adj. EBITDA | E4: EV / revenue | F4: EV / EBITDA | G4: EBITDA margin
A5: Meridian Flow Systems | B5: 1213 | C5: 612.4 | D5: 118.9 | E5: =B5/C5 -> 1.9807315 | F5: =B5/D5 -> 10.20185 | G5: =D5/C5 -> 0.19415415
A6: Halden Controls plc | B6: 1591 | C6: 796.1 | D6: 143.3 | E6: =B6/C6 -> 1.9984927 | F6: =B6/D6 -> 11.102582 | G6: =D6/C6 -> 0.18000251
A7: Portsend Industrial | B7: 547 | C7: 341.7 | D7: 61.5 | E7: =B7/C7 -> 1.6008194 | F7: =B7/D7 -> 8.8943089 | G7: =D7/C7 -> 0.17998244
A8: Kestrel Valve Group | B8: 937 | C8: 428.9 | D8: 90.1 | E8: =B8/C8 -> 2.1846584 | F8: =B8/D8 -> 10.399556 | G8: =D8/C8 -> 0.21007228
A9: Arbor Fluid Technologies | B9: 385 | C9: 268.3 | D9: 47 | E9: =B9/C9 -> 1.4349609 | F9: =B9/D9 -> 8.1914894 | G9: =D9/C9 -> 0.17517704
A10: Linden Precision Corp | B10: 683 | C10: 395.2 | D10: 71.1 | E10: =B10/C10 -> 1.7282389 | F10: =B10/D10 -> 9.6061885 | G10: =D10/C10 -> 0.17990891
A12: Mean | E12: =AVERAGE(E5:E10) -> 1.821317 | F12: =AVERAGE(F5:F10) -> 9.7326625 | G12: =AVERAGE(G5:G10) -> 0.18654955
A13: Median | E13: =MEDIAN(E5:E10) -> 1.8544852 | F13: =MEDIAN(F5:F10) -> 9.9040194 | G13: =MEDIAN(G5:G10) -> 0.17999248
A14: Low | E14: =MIN(E5:E10) -> 1.4349609 | F14: =MIN(F5:F10) -> 8.1914894 | G14: =MIN(G5:G10) -> 0.17517704
A15: High | E15: =MAX(E5:E10) -> 2.1846584 | F15: =MAX(F5:F10) -> 11.102582 | G15: =MAX(G5:G10) -> 0.21007228
A17: Implied valuation - Cascade Industrial Holdings
A18: FY2025A adjusted EBITDA | B18: =Model!D26 -> 48.9
A19: Median peer EV / EBITDA | B19: =F13 -> 9.9040194
A20: Implied enterprise value | B20: =B18*B19 -> 484.30655

Sheet Outputs
A1: Deck Outputs - every figure presented in the pitchbook
A2: Each row is one figure that appears on a slide. The deck should agree with this sheet.
A4: Ref | B4: Figure | C4: Value | D4: Source | E4: Basis
A5: O1 | B5: FY2025A revenue | C5: =Model!D6 -> 228.9 | D5: Model!D6 | E5: Reported
A6: O2 | B6: FY2025A revenue growth | C6: =Model!D7 -> 0.11822179 | D6: Model!D7 | E6: Reported
A7: O3 | B7: FY2025A gross margin | C7: =Model!D11 -> 0.38182612 | D7: Model!D11 | E7: Reported
A8: O4 | B8: FY2025A reported EBITDA | C8: =Model!D16 -> 41.2 | D8: Model!D16 | E8: Reported
A9: O5 | B9: FY2025A adjusted EBITDA | C9: =Model!D26 -> 48.9 | D9: Model!D25 | E9: Adjusted - see bridge
A10: O6 | B10: FY2025A adjusted EBITDA margin | C10: =Model!D27 -> 0.21363041 | D10: Model!D26 | E10: Adjusted
A11: O7 | B11: FY2026E revenue | C11: =Model!E6 -> 255.9102 | D11: Model!E6 | E11: Management plan
A12: O8 | B12: FY2026E adjusted EBITDA | C12: =Model!E26 -> 51.18204 | D12: Model!E25 | E12: Management plan
A13: O9 | B13: FY2030E revenue | C13: =Model!I6 -> 356.84535 | D13: Model!I6 | E13: Management plan
A14: O10 | B14: FY2030E adjusted EBITDA | C14: =Model!I26 -> 71.369071 | D14: Model!I25 | E14: Management plan
A15: O11 | B15: Revenue CAGR FY2025A-FY2030E | C15: =(Model!I6/Model!D6)^(1/5)-1 -> 0.092865838 | D15: Model!D6, I6 | E15: Computed
A16: O12 | B16: Total FY2025A EBITDA adjustments | C16: =Model!D24 -> 7.7 | D16: Model!D24 | E16: Adjustment total
A17: O13 | B17: DCF enterprise value | C17: =DCF!B16 -> 489.45287 | D17: DCF!B16 | E17: DCF, Gordon growth
A18: O14 | B18: DCF equity value | C18: =DCF!B19 -> 414.75287 | D18: DCF!B19 | E18: DCF
A19: O15 | B19: DCF implied value per share | C19: =DCF!B21 -> 9.6904876 | D19: DCF!B21 | E19: DCF
A20: O16 | B20: DCF implied EV / FY2025A adj. EBITDA | C20: =DCF!B23 -> 10.009261 | D20: DCF!B23 | E20: DCF
A21: O17 | B21: WACC | C21: =Assumptions!B19 -> 0.098 | D21: Assumptions!B19 | E21: Input
A22: O18 | B22: Terminal growth rate | C22: =Assumptions!B20 -> 0.025 | D22: Assumptions!B20 | E22: Input
A23: O19 | B23: Peer median EV / EBITDA | C23: =Comps!F13 -> 9.9040194 | D23: Comps!F13 | E23: Trading comps
A24: O20 | B24: Peer mean EV / EBITDA | C24: =Comps!F12 -> 9.7326625 | D24: Comps!F12 | E24: Trading comps
A25: O21 | B25: Comps-implied enterprise value | C25: =Comps!B20 -> 484.30655 | D25: Comps!B20 | E25: Trading comps
A26: O22 | B26: Total debt | C26: =Assumptions!B24 -> 96.4 | D26: Assumptions!B24 | E26: Balance sheet
A27: O23 | B27: Cash and equivalents | C27: =Assumptions!B25 -> 21.7 | D27: Assumptions!B25 | E27: Balance sheet
